setup.cfg
setup.py
oleg/__init__.py
oleg/engine.py
oleg.egg-info/PKG-INFO
oleg.egg-info/SOURCES.txt
oleg.egg-info/dependency_links.txt
oleg.egg-info/not-zip-safe
oleg.egg-info/top_level.txt