Metadata-Version: 1.0
Name: oleg
Version: 0.1.1
Summary: oleg
Home-page: UNKNOWN
Author: UNKNOWN
Author-email: aleksandrparnuk7@gmail.com
License: UNKNOWN
Platform: UNKNOWN
